{"cookies": [], "origins": [{"origin": "https://nikita-filonov.github.io", "localStorage": [{"name": "persist:users", "value": "{\"user\":\"{\\\"id\\\":\\\"38a1ab60-7cc0-4206-abfa-f70fab21b7bd\\\",\\\"email\\\":\\\"user.name@gmail.com\\\",\\\"username\\\":\\\"username\\\",\\\"password\\\":\\\"password\\\"}\",\"users\":\"[{\\\"id\\\":\\\"38a1ab60-7cc0-4206-abfa-f70fab21b7bd\\\",\\\"email\\\":\\\"user.name@gmail.com\\\",\\\"username\\\":\\\"username\\\",\\\"password\\\":\\\"password\\\"}]\",\"_persist\":\"{\\\"version\\\":-1,\\\"rehydrated\\\":true}\"}"}, {"name": "persist:courses", "value": "{\"course\":\"{\\\"id\\\":\\\"\\\",\\\"title\\\":\\\"\\\",\\\"userId\\\":\\\"\\\",\\\"maxScore\\\":0,\\\"minScore\\\":0,\\\"exercises\\\":[],\\\"description\\\":\\\"\\\",\\\"previewImage\\\":null,\\\"estimatedTime\\\":\\\"\\\"}\",\"courses\":\"[]\",\"_persist\":\"{\\\"version\\\":-1,\\\"rehydrated\\\":true}\"}"}]}]}